seqlib/__init__.py
seqlib/_seqlib.cpython-36m-darwin.so
seqlib-0.0.6.dist-info/DESCRIPTION.rst
seqlib-0.0.6.dist-info/METADATA
seqlib-0.0.6.dist-info/RECORD
seqlib-0.0.6.dist-info/WHEEL
seqlib-0.0.6.dist-info/metadata.json
seqlib-0.0.6.dist-info/top_level.txt
